LICENCE.txt
MANIFEST.in
README.md
requirements.dev.txt
requirements.txt
setup.py
django_documents_tools/__init__.py
django_documents_tools/apps.py
django_documents_tools/exceptions.py
django_documents_tools/fields.py
django_documents_tools/manager.py
django_documents_tools/models.py
django_documents_tools/settings.py
django_documents_tools/signals.py
django_documents_tools/tasks.py
django_documents_tools/utils.py
django_documents_tools.egg-info/PKG-INFO
django_documents_tools.egg-info/SOURCES.txt
django_documents_tools.egg-info/dependency_links.txt
django_documents_tools.egg-info/not-zip-safe
django_documents_tools.egg-info/requires.txt
django_documents_tools.egg-info/top_level.txt
django_documents_tools/api/__init__.py
django_documents_tools/api/filters.py
django_documents_tools/api/router.py
django_documents_tools/api/serializers.py
django_documents_tools/api/viewsets.py