Metadata-Version: 2.1
Name: django-documents-tools
Version: 1.1.1
Summary: Toolset to work with documents and snapshots
Home-page: https://github.com/pik-software/documents-tools
Author: pik-software
Author-email: no-reply@pik-software.ru
License: BSD-3-Clause
Platform: UNKNOWN
Classifier: Intended Audience :: Developers
Classifier: License :: OSI Approved :: BSD License
Classifier: Programming Language :: Python :: 3.7
Classifier: Programming Language :: Python :: Implementation :: CPython
Provides-Extra: dev
License-File: LICENCE.txt
